{
  "$schema": "http://json-schema.org/draft-07/schema",
  "$id": "https://github.com/microsoft/AzureTRE/schema/workspace_service.json",
  "type": "object",
  "title": "User Resource Default Parameters",
  "description": "These parameters are required for all user resources",
  "required": [
      "display_name",
      "description"
  ],
  "properties": {
      "display_name": {
          "type": "string",
          "title": "Name for the user resource",
          "description": "The name of the user resource to be displayed to users"
      },
      "description": {
          "type": "string",
          "title": "Description of the user resource",
          "description": "Description of the user resource"
      }
  }
}